LICENSE
MANIFEST.in
README.md
requirements-dev.txt
requirements-test.txt
requirements.txt
setup.cfg
setup.py
antlr4_vba_parser/__init__.py
antlr4_vba_parser/antlr-4.9.2-complete.jar
antlr4_vba_parser/vba.interp
antlr4_vba_parser/vba.tokens
antlr4_vba_parser/vbaLexer.interp
antlr4_vba_parser/vbaLexer.py
antlr4_vba_parser/vbaLexer.tokens
antlr4_vba_parser/vbaListener.py
antlr4_vba_parser/vbaParser.py
antlr4_vba_parser/vba_listener.py
antlr4_vba_parser/vba_parser.py
antlr4_vba_parser.egg-info/PKG-INFO
antlr4_vba_parser.egg-info/SOURCES.txt
antlr4_vba_parser.egg-info/dependency_links.txt
antlr4_vba_parser.egg-info/entry_points.txt
antlr4_vba_parser.egg-info/requires.txt
antlr4_vba_parser.egg-info/top_level.txt